{
    "1": "filter_by_New",
    "2": "show_next_slides",
    "3": "search_by_searchbar",
    "4": " redirecting to powerful bussiness writing :how to write concisely",
    "5": "redirect_to_business_strategy",
    "6": "redirect_to_communications_page",
    "7": "redirect_to_Operations",
    "8": "redirect_to_trending_options",
    "9": "option_link",
    "10": "chooses_option",
    "11": "redirect_to_Post_Management",
    "12": "redirect_to_business_law",
    "13": "search_button",
    "14": "redirect_to_Udemy_Page",
    "15": "redirect_to_Entrepreneurship",
    "16": "redirect_to_introduction_to_business_page",
    "17": "filter_by_sales_course_topic"
}