{
    "1": "browse_mystery",
    "2": "browse_kids",
    "3": "browse_non_fiction",
    "4": "browse_romance",
    "5": "browse_adult",
    "6": "browse_adult",
    "7": "see_more_paid_books",
    "8": "see_more_free_books",
    "9": "see_more_ny_times_fiction",
    "10": "see_more_ny_times_non_fiction",
    "11": "read_schoolhouse",
    "12": "read_holly",
    "13": "read_outlive",
    "14": "read_dreamland",
    "15": "read_elon_musk",
    "16": "browse_sections",
    "17": "pdf_directory",
    "18": "finished_directory",
    "19": "want_to_read_directory",
    "20": "search_option",
    "21": "read_mystery_guest",
    "22": "read_golden_gate",
    "23": "see_all_coming_soon",
    "24": "see_more_to_explore",
    "25": "scroll",
    "26": "audiobooks_directory",
    "27": "create_new_collection",
    "28": "my_books_directory"
}