{
    "example_0": {
        "top_left": [
            1300,
            216
        ],
        "bottom_right": [
            1668,
            259
        ],
        "label": "type event name"
    },
    "example_1": {
        "top_left": [
            1680,
            215
        ],
        "bottom_right": [
            1719,
            260
        ],
        "label": "checkbox all day"
    },
    "example_2": {
        "top_left": [
            1224,
            216
        ],
        "bottom_right": [
            1291,
            263
        ],
        "label": "event type select"
    },
    "example_3": {
        "top_left": [
            1261,
            292
        ],
        "bottom_right": [
            1511,
            330
        ],
        "label": "event start time"
    },
    "example_4": {
        "top_left": [
            1541,
            291
        ],
        "bottom_right": [
            1775,
            331
        ],
        "label": "Event end time"
    },
    "example_5": {
        "top_left": [
            1261,
            348
        ],
        "bottom_right": [
            1774,
            384
        ],
        "label": "Event location"
    },
    "example_6": {
        "top_left": [
            1384,
            404
        ],
        "bottom_right": [
            1570,
            434
        ],
        "label": "Event reminder options"
    },
    "example_7": {
        "top_left": [
            1518,
            463
        ],
        "bottom_right": [
            1645,
            500
        ],
        "label": "more details"
    },
    "example_8": {
        "top_left": [
            1659,
            463
        ],
        "bottom_right": [
            1775,
            502
        ],
        "label": "Save event"
    },
    "example_9": {
        "top_left": [
            1213,
            163
        ],
        "bottom_right": [
            1476,
            191
        ],
        "label": "change event account"
    },
    "example_10": {
        "top_left": [
            1745,
            161
        ],
        "bottom_right": [
            1788,
            192
        ],
        "label": "cancel event "
    },
    "example_11": {
        "top_left": [
            1057,
            47
        ],
        "bottom_right": [
            1156,
            97
        ],
        "label": "Today"
    },
    "example_12": {
        "top_left": [
            1180,
            47
        ],
        "bottom_right": [
            1263,
            95
        ],
        "label": "View daily"
    },
    "example_13": {
        "top_left": [
            1272,
            47
        ],
        "bottom_right": [
            1377,
            96
        ],
        "label": "View Weekly"
    },
    "example_14": {
        "top_left": [
            1386,
            48
        ],
        "bottom_right": [
            1486,
            97
        ],
        "label": "View Monthly"
    },
    "example_15": {
        "top_left": [
            1501,
            48
        ],
        "bottom_right": [
            1592,
            94
        ],
        "label": "View yearly"
    },
    "example_16": {
        "top_left": [
            1666,
            53
        ],
        "bottom_right": [
            1729,
            87
        ],
        "label": "Toggle new outlook"
    },
    "example_17": {
        "top_left": [
            337,
            45
        ],
        "bottom_right": [
            375,
            88
        ],
        "label": "Previous day"
    },
    "example_18": {
        "top_left": [
            386,
            46
        ],
        "bottom_right": [
            424,
            88
        ],
        "label": "Next day"
    },
    "example_19": {
        "top_left": [
            14,
            112
        ],
        "bottom_right": [
            212,
            150
        ],
        "label": "New event"
    },
    "example_20": {
        "top_left": [
            222,
            174
        ],
        "bottom_right": [
            266,
            211
        ],
        "label": "Previous month"
    },
    "example_21": {
        "top_left": [
            267,
            173
        ],
        "bottom_right": [
            307,
            212
        ],
        "label": "Next month"
    }
}